snsync/__init__.py
snsync/__main__.py
snsync/config.py
snsync/converter/__init__.py
snsync/converter/note2pdf.py
snsync/converter/spd2png.py
snsync/db.py
snsync/schema.py
snsync/service.py
snsync/supernote.py
snsync/sync.py
supernote_sync-0.3.3.dist-info/LICENSE
supernote_sync-0.3.3.dist-info/METADATA
supernote_sync-0.3.3.dist-info/WHEEL
supernote_sync-0.3.3.dist-info/entry_points.txt
supernote_sync-0.3.3.dist-info/RECORD
