Metadata-Version: 2.3
Name: supernote-sync
Version: 0.3.3
Summary: Automatically sync Supernote notebooks and convert to PDF on local WiFi
License: Apache-2.0
Author: Jerome Boisvert-Chouinard
Author-email: github@jbchouinard.net
Requires-Python: >=3.11,<4
Classifier: License :: OSI Approved :: Apache Software License
Classifier: Programming Language :: Python :: 3
Classifier: Programming Language :: Python :: 3.11
Classifier: Programming Language :: Python :: 3.12
Classifier: Programming Language :: Python :: 3.13
Requires-Dist: loguru (>=0.7.3,<0.8.0)
Requires-Dist: pydantic (>=2.11.7,<3.0.0)
Requires-Dist: pydantic-settings (>=2.10.1,<3.0.0)
Requires-Dist: reportlab (>=4.4.2,<5.0.0)
Requires-Dist: requests (>=2.32.4,<3.0.0)
Requires-Dist: sn2md (>=2.3.2,<3.0.0)
Requires-Dist: sqlalchemy (>=2.0.41,<3.0.0)
Requires-Dist: supernotelib (>=0.6.2,<0.7.0)
Requires-Dist: tabulate (>=0.9.0,<0.10.0)
Project-URL: Homepage, https://github.com/jbchouinard/supernote-sync
Project-URL: Issues, https://github.com/jbchouinard/supernote-sync/issues
Project-URL: Repository, https://github.com/jbchouinard/supernote-sync
